time_mcp_local/__init__.py
time_mcp_local/__main__.py
time_mcp_local/server.py
time_mcp_local-0.1.3.dist-info/METADATA
time_mcp_local-0.1.3.dist-info/WHEEL
time_mcp_local-0.1.3.dist-info/entry_points.txt
time_mcp_local-0.1.3.dist-info/RECORD
