Metadata-Version: 2.4
Name: time-mcp-local
Version: 0.1.3
Summary: Add your description here
Requires-Python: >=3.12
Requires-Dist: mcp>=1.3.0
Requires-Dist: pydantic>=2.10.6
Requires-Dist: tzdata>=2025.1
Requires-Dist: tzlocal>=5.3
